keyimstr/__init__.py
keyimstr/keyimstr.py
Keyimstr-0.0.1.dist-info/LICENSE
Keyimstr-0.0.1.dist-info/METADATA
Keyimstr-0.0.1.dist-info/WHEEL
Keyimstr-0.0.1.dist-info/top_level.txt
Keyimstr-0.0.1.dist-info/RECORD
