Metadata-Version: 2.1
Name: Keyimstr
Version: 0.0.1
Summary: Numpy <-> Bytes <-> String
Home-page: https://github.com/keywind127/image-string-converter
Author: Keywind
Author-email: watersprayer127@gmail.com
Project-URL: Bug Tracker, https://github.com/keywind127/image-string-converter/issues
Classifier: Programming Language :: Python :: 3
Classifier: License :: OSI Approved :: MIT License
Classifier: Operating System :: OS Independent
Requires-Python: >=3.6
License-File: LICENSE
Requires-Dist: markdown
Requires-Dist: numpy
Requires-Dist: opencv-python
